README.rst
nameko_socket_server.py
setup.py
nameko_socket_server.egg-info/PKG-INFO
nameko_socket_server.egg-info/SOURCES.txt
nameko_socket_server.egg-info/dependency_links.txt
nameko_socket_server.egg-info/requires.txt
nameko_socket_server.egg-info/top_level.txt
nameko_socket_server.egg-info/zip-safe
test/test_nameko_socket_server.py