Metadata-Version: 1.1
Name: nameko-socket-server
Version: 0.1.1
Summary: Socket server entrypoints for nameko services
Home-page: http://github.com/onefinestay/nameko-socket-server
Author: onefinestay
Author-email: engineering@onefinestay.com
License: Apache License, Version 2.0
Platform: UNKNOWN
Classifier: Programming Language :: Python
Classifier: Operating System :: MacOS :: MacOS X
Classifier: Operating System :: POSIX
Classifier: Programming Language :: Python :: 2.7
Classifier: Topic :: Internet
Classifier: Topic :: Software Development :: Libraries :: Python Modules
Classifier: Intended Audience :: Developers
